matsci_opt_benchmarks/crabnet_hyperparameter/__init__.py
matsci_opt_benchmarks/crabnet_hyperparameter/core.py
matsci_opt_benchmarks/crabnet_hyperparameter/utils/parameters.py
matsci_opt_benchmarks/crabnet_hyperparameter/utils/plotting.py
matsci_opt_benchmarks/crabnet_hyperparameter/utils/validation.py
matsci_opt_benchmarks/particle_packing/__init__.py
matsci_opt_benchmarks/particle_packing/core.py
matsci_opt_benchmarks/particle_packing/utils/PackingGeneration.exe
matsci_opt_benchmarks/particle_packing/utils/__init__.py
matsci_opt_benchmarks/particle_packing/utils/ax.py
matsci_opt_benchmarks/particle_packing/utils/data.py
matsci_opt_benchmarks/particle_packing/utils/packing_generation.py
matsci_opt_benchmarks/particle_packing/utils/particle_packing.py
matsci_opt_benchmarks/particle_packing/utils/plotting.py
matsci_opt_benchmarks-0.2.3.dist-info/LICENSE.txt
matsci_opt_benchmarks-0.2.3.dist-info/METADATA
matsci_opt_benchmarks-0.2.3.dist-info/WHEEL
matsci_opt_benchmarks-0.2.3.dist-info/top_level.txt
matsci_opt_benchmarks-0.2.3.dist-info/RECORD
