Metadata-Version: 2.1
Name: matsci-opt-benchmarks
Version: 0.2.3
Summary: A collection of benchmarking problems and datasets for testing the performance of advanced optimization algorithms in the field of materials science and chemistry.
Home-page: https://github.com/sparks-baird/matsci-opt-benchmarks
Author: Sterling Baird
Author-email: sterling.baird@utah.edu
License: MIT
Project-URL: Documentation, https://matsci-opt-benchmarks.readthedocs.io
Project-URL: Source, https://github.com/sparks-baird/matsci-opt-benchmarks
Platform: any
Classifier: Development Status :: 4 - Beta
Classifier: Programming Language :: Python
License-File: LICENSE.txt
Requires-Dist: numpy
Requires-Dist: pandas
Requires-Dist: scipy
Requires-Dist: cloudpickle
Requires-Dist: requests
Requires-Dist: crabnet (==2.0.8)
Requires-Dist: matbench
Requires-Dist: torch (<2.0)
Requires-Dist: zenodo-client
Requires-Dist: ray[tune]
Requires-Dist: kaleido
Requires-Dist: xtal2png
Requires-Dist: ax-platform
Requires-Dist: importlib-metadata ; python_version < "3.8"
Provides-Extra: testing
Requires-Dist: setuptools ; extra == 'testing'
Requires-Dist: pytest ; extra == 'testing'
Requires-Dist: pytest-cov ; extra == 'testing'
